{
  "swagger": "2.0",
  "info": {
    "title": "Book Box",
    "description": "Description",
    "version": "1.0.0"
  },
  "host": "localhost:3000",
  "basePath": "/",
  "schemes": [
    "http"
  ],
  "paths": {
    "/": {
      "get": {
        "description": "",
        "parameters": [],
        "responses": {
          "200": {
            "description": "OK"
          }
        }
      }
    },
    "/books/": {
      "get": {
        "description": "",
        "parameters": [],
        "responses": {
          "200": {
            "description": "OK"
          },
          "500": {
            "description": "Internal Server Error"
          }
        }
      },
      "post": {
        "description": "",
        "parameters": [
          {
            "name": "body",
            "in": "body",
            "schema": {
              "type": "object",
              "properties": {
                "title": {
                  "example": "any"
                },
                "author": {
                  "example": "any"
                },
                "rating": {
                  "example": "any"
                },
                "description": {
                  "example": "any"
                },
                "imageUrl": {
                  "example": "any"
                },
                "dateRead": {
                  "example": "any"
                }
              }
            }
          }
        ],
        "responses": {
          "201": {
            "description": "Created"
          },
          "500": {
            "description": "Internal Server Error"
          }
        }
      }
    },
    "/books/{id}": {
      "get": {
        "description": "",
        "parameters": [
          {
            "name": "id",
            "in": "path",
            "required": true,
            "type": "string"
          }
        ],
        "responses": {
          "200": {
            "description": "OK"
          },
          "500": {
            "description": "Internal Server Error"
          }
        }
      },
      "put": {
        "description": "",
        "parameters": [
          {
            "name": "id",
            "in": "path",
            "required": true,
            "type": "string"
          },
          {
            "name": "body",
            "in": "body",
            "schema": {
              "type": "object",
              "properties": {
                "title": {
                  "example": "any"
                },
                "author": {
                  "example": "any"
                },
                "rating": {
                  "example": "any"
                },
                "description": {
                  "example": "any"
                },
                "imageUrl": {
                  "example": "any"
                },
                "dateRead": {
                  "example": "any"
                }
              }
            }
          }
        ],
        "responses": {
          "204": {
            "description": "No Content"
          },
          "500": {
            "description": "Internal Server Error"
          }
        }
      },
      "delete": {
        "description": "",
        "parameters": [
          {
            "name": "id",
            "in": "path",
            "required": true,
            "type": "string"
          }
        ],
        "responses": {
          "204": {
            "description": "No Content"
          },
          "500": {
            "description": "Internal Server Error"
          }
        }
      }
    }
  }
}